{
  "routes": [
    {
      "method": "GET",
      "path": "/pods",
      "handler": "pod.find",
      "config": {
        "policies": []
      }
    },
    {
      "method": "GET",
      "path": "/pods/count",
      "handler": "pod.count",
      "config": {
        "policies": []
      }
    },
    {
      "method": "GET",
      "path": "/pods/:id",
      "handler": "pod.findOne",
      "config": {
        "policies": []
      }
    },
    {
      "method": "POST",
      "path": "/pods",
      "handler": "pod.create",
      "config": {
        "policies": []
      }
    },
    {
      "method": "PUT",
      "path": "/pods/:id",
      "handler": "pod.update",
      "config": {
        "policies": []
      }
    },
    {
      "method": "DELETE",
      "path": "/pods/:id",
      "handler": "pod.delete",
      "config": {
        "policies": []
      }
    }
  ]
}
